tvi/solphit/ingialla/__init__.py
tvi/solphit/ingialla/ask.py
tvi/solphit/ingialla/chunk.py
tvi/solphit/ingialla/clean.py
tvi/solphit/ingialla/embed.py
tvi/solphit/ingialla/es.py
tvi/solphit/ingialla/kb.py
tvi/solphit/ingialla/parsing.py
tvi/solphit/ingialla/wikidump.py
tvi_solphit_ingialla-0.3.0.dist-info/licenses/LICENSE
tvi_solphit_ingialla-0.3.0.dist-info/METADATA
tvi_solphit_ingialla-0.3.0.dist-info/WHEEL
tvi_solphit_ingialla-0.3.0.dist-info/top_level.txt
tvi_solphit_ingialla-0.3.0.dist-info/RECORD
