Metadata-Version: 2.4
Name: tvi-solphit-ingialla
Version: 0.3.0
Summary: Ingialla domain logic: ES backend, wikidump split, parsing/cleaning, chunking, embeddings, ask/KB build.
Author: Tobias Hagenbeek
License: MIT License
Requires-Python: >=3.9
License-File: LICENSE
Requires-Dist: tvi-solphit-base>=0.2.0
Requires-Dist: elasticsearch>=8.11
Requires-Dist: lxml
Requires-Dist: tqdm
Requires-Dist: numpy
Requires-Dist: requests
Provides-Extra: st
Requires-Dist: sentence-transformers>=2.6.0; extra == "st"
Provides-Extra: ollama
Dynamic: license-file
